odoo/addons/shopinvader_restapi/README.rst
odoo/addons/shopinvader_restapi/__init__.py
odoo/addons/shopinvader_restapi/__manifest__.py
odoo/addons/shopinvader_restapi/hooks.py
odoo/addons/shopinvader_restapi/shopinvader_response.py
odoo/addons/shopinvader_restapi/utils.py
odoo/addons/shopinvader_restapi/components/__init__.py
odoo/addons/shopinvader_restapi/components/access_info.py
odoo/addons/shopinvader_restapi/components/core.py
odoo/addons/shopinvader_restapi/components/service_context_provider.py
odoo/addons/shopinvader_restapi/data/cart_step.xml
odoo/addons/shopinvader_restapi/data/mail_activity_data.xml
odoo/addons/shopinvader_restapi/data/queue_job_channel_data.xml
odoo/addons/shopinvader_restapi/data/queue_job_function_data.xml
odoo/addons/shopinvader_restapi/data/res_partner.xml
odoo/addons/shopinvader_restapi/demo/account_demo.xml
odoo/addons/shopinvader_restapi/demo/backend_demo.xml
odoo/addons/shopinvader_restapi/demo/email_demo.xml
odoo/addons/shopinvader_restapi/demo/notification_demo.xml
odoo/addons/shopinvader_restapi/demo/partner_demo.xml
odoo/addons/shopinvader_restapi/demo/pricelist_demo.xml
odoo/addons/shopinvader_restapi/demo/sale_demo.xml
odoo/addons/shopinvader_restapi/i18n/shopinvader.pot
odoo/addons/shopinvader_restapi/i18n/shopinvader_restapi.pot
odoo/addons/shopinvader_restapi/models/__init__.py
odoo/addons/shopinvader_restapi/models/account_move.py
odoo/addons/shopinvader_restapi/models/res_config_settings.py
odoo/addons/shopinvader_restapi/models/res_partner.py
odoo/addons/shopinvader_restapi/models/sale.py
odoo/addons/shopinvader_restapi/models/shopinvader_backend.py
odoo/addons/shopinvader_restapi/models/shopinvader_cart_step.py
odoo/addons/shopinvader_restapi/models/shopinvader_notification.py
odoo/addons/shopinvader_restapi/models/shopinvader_partner.py
odoo/addons/shopinvader_restapi/models/track_external_mixin.py
odoo/addons/shopinvader_restapi/readme/CONTRIBUTORS.rst
odoo/addons/shopinvader_restapi/readme/CREDITS.rst
odoo_addon_shopinvader_restapi-16.0.1.1.3.6.dist-info/METADATA
odoo_addon_shopinvader_restapi-16.0.1.1.3.6.dist-info/WHEEL
odoo_addon_shopinvader_restapi-16.0.1.1.3.6.dist-info/top_level.txt
odoo_addon_shopinvader_restapi-16.0.1.1.3.6.dist-info/RECORD
