Metadata-Version: 2.1
Name: odoo-addon-shopinvader_restapi
Version: 16.0.1.1.3.6
Summary: Shopinvader
Home-page: https://github.com/shopinvader/odoo-shopinvader
Author: Akretion,ACSONE SA/NV
License: AGPL-3
Classifier: Programming Language :: Python
Classifier: Framework :: Odoo
Classifier: Framework :: Odoo :: 16.0
Classifier: License :: OSI Approved :: GNU Affero General Public License v3
Classifier: Development Status :: 3 - Alpha
Requires-Python: >=3.10
Requires-Dist: cerberus
Requires-Dist: odoo-addon-base-rest<16.1dev,>=16.0dev
Requires-Dist: odoo-addon-base-sparse-field-list-support<16.1dev,>=16.0dev
Requires-Dist: odoo-addon-component-event<16.1dev,>=16.0dev
Requires-Dist: odoo-addon-jsonifier<16.1dev,>=16.0dev
Requires-Dist: odoo-addon-onchange-helper<16.1dev,>=16.0dev
Requires-Dist: odoo-addon-queue-job<16.1dev,>=16.0dev
Requires-Dist: odoo-addon-sale-cart<16.1dev,>=16.0dev
Requires-Dist: odoo-addon-sale-discount-display-amount<16.1dev,>=16.0dev
Requires-Dist: odoo-addon-server-environment<16.1dev,>=16.0dev
Requires-Dist: odoo-addon-shopinvader-sale-state<16.1dev,>=16.0dev
Requires-Dist: odoo<16.1dev,>=16.0a
Requires-Dist: unidecode
